CHANGES.txt
Kookbook.py
MANIFEST
MANIFEST.in
MIT-LICENSE
README.txt
setup.py
lib/oktest.py
lib/Oktest.egg-info/PKG-INFO
lib/Oktest.egg-info/SOURCES.txt
lib/Oktest.egg-info/dependency_links.txt
lib/Oktest.egg-info/top_level.txt
test/assertions_test.py
test/context_test.py
test/doc_test.py
test/dummy_test.py
test/mainapp_test.py
test/reporter_test.py
test/runner_test.py
test/skip_test.py
test/spec_test.py
test/testdeco_test.py
test/todo_test.py
test/tracer_test.py
test/util_test.py